BuildYourApplicationsWithWebpack/README.md
BuildYourApplicationsWithWebpack/__init__.py
BuildYourApplicationsWithWebpack/__main__.py
BuildYourApplicationsWithWebpack/file.epub
BuildYourApplicationsWithWebpack/index.html
BuildYourApplicationsWithWebpack/css/__init__.py
BuildYourApplicationsWithWebpack/css/annotations.css
BuildYourApplicationsWithWebpack/css/main.css
BuildYourApplicationsWithWebpack/css/normalize.css
BuildYourApplicationsWithWebpack/css/popup.css
BuildYourApplicationsWithWebpack/font/__init__.py
BuildYourApplicationsWithWebpack/font/fontello.eot
BuildYourApplicationsWithWebpack/font/fontello.svg
BuildYourApplicationsWithWebpack/font/fontello.ttf
BuildYourApplicationsWithWebpack/font/fontello.woff
BuildYourApplicationsWithWebpack/img/__init__.py
BuildYourApplicationsWithWebpack/img/annotator-glyph-sprite.png
BuildYourApplicationsWithWebpack/img/annotator-icon-sprite.png
BuildYourApplicationsWithWebpack/img/apple-touch-icon.png
BuildYourApplicationsWithWebpack/img/cancelfullscreen.png
BuildYourApplicationsWithWebpack/img/close.png
BuildYourApplicationsWithWebpack/img/fullscreen.png
BuildYourApplicationsWithWebpack/img/loader.gif
BuildYourApplicationsWithWebpack/img/menu-icon.png
BuildYourApplicationsWithWebpack/img/save.png
BuildYourApplicationsWithWebpack/img/saved.png
BuildYourApplicationsWithWebpack/img/settings-s.png
BuildYourApplicationsWithWebpack/img/settings.png
BuildYourApplicationsWithWebpack/img/star.png
BuildYourApplicationsWithWebpack/js/__init__.py
BuildYourApplicationsWithWebpack/js/epub.js
BuildYourApplicationsWithWebpack/js/epub.min.js
BuildYourApplicationsWithWebpack/js/epub.min.map
BuildYourApplicationsWithWebpack/js/hooks.min.js
BuildYourApplicationsWithWebpack/js/hooks.min.map
BuildYourApplicationsWithWebpack/js/reader.js
BuildYourApplicationsWithWebpack/js/reader.js.map
BuildYourApplicationsWithWebpack/js/reader.min.js
BuildYourApplicationsWithWebpack/js/reader.min.map
BuildYourApplicationsWithWebpack/js/hooks/__init__.py
build_your_applications_with_webpack-2024.3.4.0.dist-info/METADATA
build_your_applications_with_webpack-2024.3.4.0.dist-info/WHEEL
build_your_applications_with_webpack-2024.3.4.0.dist-info/entry_points.txt
build_your_applications_with_webpack-2024.3.4.0.dist-info/top_level.txt
build_your_applications_with_webpack-2024.3.4.0.dist-info/RECORD
